dxlthehiveservice/__init__.py
dxlthehiveservice/__main__.py
dxlthehiveservice/_version.py
dxlthehiveservice/app.py
dxlthehiveservice/requesthandlers.py
dxlthehiveservice/thehive_client.py
dxlthehiveservice/_config/__init__.py
dxlthehiveservice/_config/app/__init__.py
dxlthehiveservice/_config/app/dxlclient.config
dxlthehiveservice/_config/app/dxlthehiveservice.config
dxlthehiveservice/_config/app/logging.config
dxlthehiveservice/_config/sample/__init__.py
dxlthehiveservice/_config/sample/dxlclient.config
dxlthehiveservice/_config/sample/dxlthehiveservice.config
dxlthehiveservice-0.1.0.dist-info/METADATA
dxlthehiveservice-0.1.0.dist-info/RECORD
dxlthehiveservice-0.1.0.dist-info/WHEEL
dxlthehiveservice-0.1.0.dist-info/top_level.txt
